[
  {
    "Id": "67feb4b25ce1eab6efbedc49",
    "Name": "Forest Prince",
    "Attributes": {
      "totalCost": "200",
      "category": "Characters",
      "army": "Sylvan Elves",
      "height": "Standard",
      "type": "",
      "defaultFront": "1"
    },
    "AttributeLists": {},
    "RuleIds": [],
    "OptionListIds": [
      "d015a17c-e7c7-4db8-a3ed-3b3330094b39",
      "041b2f33-544c-4fff-b3dd-6c40fb0c25de",
      "d57fdbd7-e6bf-4a8d-9c8f-0602b04ba0fb",
      "e508e2b4-b25f-4ee2-b34b-32cfacfbcf4b",
      "7cbc1212-705e-4902-9eac-551c38d6f814"
    ],
    "ProfileIds": [
      "67feb4b25ce1eab6efbedc49"
    ]
  },
  {
    "Id": "67feb4b35ce1eab6efbede58",
    "Name": "Chieftain",
    "Attributes": {
      "totalCost": "80",
      "category": "Characters",
      "army": "Sylvan Elves",
      "height": "Standard",
      "type": "",
      "defaultFront": "1"
    },
    "AttributeLists": {},
    "RuleIds": [],
    "OptionListIds": [
      "6895d9b7-adf5-4f1b-b0b0-e65e74751928",
      "10088bdb-a136-4dce-a63e-99856e75663f",
      "65c46fd4-5aff-4907-9246-a6e239f9dc43",
      "2e45206e-5286-474f-84f2-603c54508cf1"
    ],
    "ProfileIds": [
      "67feb4b35ce1eab6efbede58"
    ]
  },
  {
    "Id": "67feb4b35ce1eab6efbee029",
    "Name": "Druid",
    "Attributes": {
      "totalCost": "270",
      "category": "Characters",
      "army": "Sylvan Elves",
      "height": "Standard",
      "type": "",
      "defaultFront": "1"
    },
    "AttributeLists": {},
    "RuleIds": [],
    "OptionListIds": [
      "46dabbed-5da2-4fb9-8697-57eaa5ac93e6",
      "7e6c8c3f-dbae-41c8-8c84-4f29e9157232",
      "81b983f1-5b36-4ecb-950f-ca1574f22b1a",
      "955826ef-860f-488d-841b-12ce510e85b4",
      "1f5004b1-f1d0-4c2e-86a3-806f1d97b925"
    ],
    "ProfileIds": [
      "67feb4b35ce1eab6efbee029"
    ]
  },
  {
    "Id": "67feb4b45ce1eab6efbee1b1",
    "Name": "Treefather Ancient",
    "Attributes": {
      "totalCost": "560",
      "category": "Characters",
      "army": "Sylvan Elves",
      "height": "Gigantic",
      "type": "",
      "defaultFront": "1"
    },
    "AttributeLists": {},
    "RuleIds": [],
    "OptionListIds": [],
    "ProfileIds": [
      "67feb4b45ce1eab6efbee1b1"
    ]
  },
  {
    "Id": "67feb4b55ce1eab6efbee1ca",
    "Name": "Avatar of Nature",
    "Attributes": {
      "totalCost": "560",
      "category": "Characters",
      "army": "Sylvan Elves",
      "height": "Gigantic",
      "type": "",
      "defaultFront": "1"
    },
    "AttributeLists": {},
    "RuleIds": [],
    "OptionListIds": [],
    "ProfileIds": [
      "67feb4b55ce1eab6efbee1ca"
    ]
  },
  {
    "Id": "67feb4b55ce1eab6efbee1db",
    "Name": "Dryad Ancient",
    "Attributes": {
      "totalCost": "80",
      "category": "Characters",
      "army": "Sylvan Elves",
      "height": "Standard",
      "type": "",
      "defaultFront": "1"
    },
    "AttributeLists": {},
    "RuleIds": [],
    "OptionListIds": [],
    "ProfileIds": [
      "67feb4b55ce1eab6efbee1db"
    ]
  },
  {
    "Id": "67feb4b55ce1eab6efbee1f5",
    "Name": "Thicket Shepherd",
    "Attributes": {
      "totalCost": "200",
      "category": "Characters",
      "army": "Sylvan Elves",
      "height": "Large",
      "type": "",
      "defaultFront": "1"
    },
    "AttributeLists": {},
    "RuleIds": [],
    "OptionListIds": [],
    "ProfileIds": [
      "67feb4b55ce1eab6efbee1f5"
    ]
  },
  {
    "Id": "67feb4b55ce1eab6efbee207",
    "Name": "Forest Guard",
    "Attributes": {
      "totalCost": "-13",
      "category": "Core Units",
      "army": "Sylvan Elves",
      "height": "Standard",
      "type": "",
      "defaultFront": "5"
    },
    "AttributeLists": {},
    "RuleIds": [],
    "OptionListIds": [
      "cb8130e2-44a5-4232-97f5-8a802109e1e6",
      "d9b232d7-8542-48c9-a1cd-a29822d136b0"
    ],
    "ProfileIds": [
      "67feb4b55ce1eab6efbee209"
    ]
  },
  {
    "Id": "67feb4b65ce1eab6efbee23a",
    "Name": "Sylvan Archers",
    "Attributes": {
      "totalCost": "87",
      "category": "Core Units",
      "army": "Sylvan Elves",
      "height": "Standard",
      "type": "",
      "defaultFront": "5"
    },
    "AttributeLists": {},
    "RuleIds": [],
    "OptionListIds": [
      "e57e1250-7fa0-40fb-96ea-aa2b6e42bd8f",
      "205a9226-d450-4fe2-8695-b8902020e0e1"
    ],
    "ProfileIds": [
      "67feb4b65ce1eab6efbee23c"
    ]
  },
  {
    "Id": "67feb4b65ce1eab6efbee26a",
    "Name": "Heath Riders",
    "Attributes": {
      "totalCost": "73",
      "category": "Core Units",
      "army": "Sylvan Elves",
      "height": "Standard",
      "type": "",
      "defaultFront": "5"
    },
    "AttributeLists": {},
    "RuleIds": [],
    "OptionListIds": [
      "8fd34d0b-f83d-4b9a-80cd-3cc0bbe41c99",
      "8a2041e7-df2c-4b4d-ba04-acdf7998cbf2"
    ],
    "ProfileIds": [
      "67feb4b65ce1eab6efbee26c"
    ]
  },
  {
    "Id": "67feb4b75ce1eab6efbee2a6",
    "Name": "Dryads",
    "Attributes": {
      "totalCost": "35",
      "category": "Core Units",
      "army": "Sylvan Elves",
      "height": "Standard",
      "type": "",
      "defaultFront": "5"
    },
    "AttributeLists": {},
    "RuleIds": [],
    "OptionListIds": [
      "6e227675-6f4b-4e97-a073-f4cd5f7bf2cb",
      "1e1d36a9-3f64-4742-a4ba-9e2f202bd5fe"
    ],
    "ProfileIds": [
      "67feb4b75ce1eab6efbee2a8"
    ]
  },
  {
    "Id": "67feb4b75ce1eab6efbee2c4",
    "Name": "Forest Rangers",
    "Attributes": {
      "totalCost": "0",
      "category": "Special",
      "army": "Sylvan Elves",
      "height": "Standard",
      "type": "",
      "defaultFront": "5"
    },
    "AttributeLists": {},
    "RuleIds": [],
    "OptionListIds": [
      "13b2bb67-6f86-4817-b6f8-29fe6fd29084",
      "1266cba3-e057-429f-bab0-f1be8305e98c"
    ],
    "ProfileIds": [
      "67feb4b75ce1eab6efbee2c6"
    ]
  },
  {
    "Id": "67feb4b75ce1eab6efbee2fa",
    "Name": "Thicket Beasts",
    "Attributes": {
      "totalCost": "0",
      "category": "Special",
      "army": "Sylvan Elves",
      "height": "Large",
      "type": "",
      "defaultFront": "3"
    },
    "AttributeLists": {},
    "RuleIds": [],
    "OptionListIds": [
      "5c8e0cf7-f439-4746-b64a-ca88530bf7f3",
      "86531c87-4e8b-4ad4-8b95-b65fc74b6f9b"
    ],
    "ProfileIds": [
      "67feb4b75ce1eab6efbee2fc"
    ]
  },
  {
    "Id": "67feb4b85ce1eab6efbee312",
    "Name": "Forest Eagles",
    "Attributes": {
      "totalCost": "150",
      "category": "Special",
      "army": "Sylvan Elves",
      "height": "Large",
      "type": "",
      "defaultFront": "3"
    },
    "AttributeLists": {},
    "RuleIds": [],
    "OptionListIds": [],
    "ProfileIds": [
      "67feb4b85ce1eab6efbee314"
    ]
  },
  {
    "Id": "67feb4b85ce1eab6efbee317",
    "Name": "Blade Dancers",
    "Attributes": {
      "totalCost": "60",
      "category": "Special",
      "army": "Sylvan Elves",
      "height": "Standard",
      "type": "",
      "defaultFront": "5"
    },
    "AttributeLists": {},
    "RuleIds": [],
    "OptionListIds": [
      "210e88c9-ed1a-4b00-a313-8ebaab3e4646",
      "c75a4648-22a2-4b13-8d44-0741eb12b44a"
    ],
    "ProfileIds": [
      "67feb4b85ce1eab6efbee319"
    ]
  },
  {
    "Id": "67feb4b95ce1eab6efbee347",
    "Name": "Treefather",
    "Attributes": {
      "totalCost": "420",
      "category": "Special",
      "army": "Sylvan Elves",
      "height": "Gigantic",
      "type": "",
      "defaultFront": "1"
    },
    "AttributeLists": {},
    "RuleIds": [],
    "OptionListIds": [],
    "ProfileIds": [
      "67feb4b95ce1eab6efbee347"
    ]
  },
  {
    "Id": "67feb4b95ce1eab6efbee348",
    "Name": "Wild Huntsmen",
    "Attributes": {
      "totalCost": "44",
      "category": "Special",
      "army": "Sylvan Elves",
      "height": "Standard",
      "type": "",
      "defaultFront": "5"
    },
    "AttributeLists": {},
    "RuleIds": [],
    "OptionListIds": [
      "f4a519a8-c6c3-4819-a3dc-d59deed3744d",
      "0235ae63-965e-44aa-a66b-6307f109e340"
    ],
    "ProfileIds": [
      "67feb4b95ce1eab6efbee34a"
    ]
  },
  {
    "Id": "67feb4ba5ce1eab6efbee387",
    "Name": "Kestrel Knights",
    "Attributes": {
      "totalCost": "140",
      "category": "Special",
      "army": "Sylvan Elves",
      "height": "Large",
      "type": "",
      "defaultFront": "3"
    },
    "AttributeLists": {},
    "RuleIds": [],
    "OptionListIds": [
      "8f7b2584-c913-4b62-884b-ca80a98a7d57",
      "7371d26c-749e-4e05-81cb-7c00352b5b7d"
    ],
    "ProfileIds": [
      "67feb4ba5ce1eab6efbee389"
    ]
  },
  {
    "Id": "67feb4bb5ce1eab6efbee3c0",
    "Name": "Briar Maidens",
    "Attributes": {
      "totalCost": "76",
      "category": "Unseen Arrows",
      "army": "Sylvan Elves",
      "height": "Standard",
      "type": "",
      "defaultFront": "5"
    },
    "AttributeLists": {},
    "RuleIds": [],
    "OptionListIds": [
      "4bf58271-5737-4e3b-a3ff-fc25ac5e59c7",
      "5abe8cb7-7196-4610-835d-4550c1130f59"
    ],
    "ProfileIds": [
      "67feb4bb5ce1eab6efbee3c2"
    ]
  },
  {
    "Id": "67feb4bb5ce1eab6efbee3de",
    "Name": "Sylvan Sentinels",
    "Attributes": {
      "totalCost": "24",
      "category": "Unseen Arrows",
      "army": "Sylvan Elves",
      "height": "Standard",
      "type": "",
      "defaultFront": "5"
    },
    "AttributeLists": {},
    "RuleIds": [],
    "OptionListIds": [],
    "ProfileIds": [
      "67feb4bb5ce1eab6efbee3e0"
    ]
  },
  {
    "Id": "67feb4bb5ce1eab6efbee3e6",
    "Name": "Pathfinders",
    "Attributes": {
      "totalCost": "40",
      "category": "Unseen Arrows",
      "army": "Sylvan Elves",
      "height": "Standard",
      "type": "",
      "defaultFront": "5"
    },
    "AttributeLists": {},
    "RuleIds": [],
    "OptionListIds": [],
    "ProfileIds": [
      "67feb4bb5ce1eab6efbee3e8"
    ]
  }
]