[
  {
    "Id": "unit_fb77-fec9-42ed-a7fd",
    "Name": "Nagash, Supreme Lord of the Undead",
    "Attributes": {
      "category": "Monster Hero",
      "army": "Nighthaunt",
      "height": "",
      "type": "",
      "defaultFront": "1"
    },
    "AttributeLists": {
      "FullOptions": [],
      "Keywords": [
        "DEATH",
        "UNIQUE",
        "HERO",
        "MONSTER",
        "WIZARD (9)",
        "WARD (5+)",
        "FLY",
        "WARMASTER",
        "NIGHTHAUNT"
      ]
    },
    "RuleIds": {},
    "ProfileIds": [
      "profile_fb77-fec9-42ed-a7fd"
    ],
    "OptionListIds": []
  },
  {
    "Id": "unit_ea83-60f1-bd67-d25",
    "Name": "Reikenor the Grimhailer",
    "Attributes": {
      "category": "Cavalry Hero",
      "army": "Nighthaunt",
      "height": "",
      "type": "",
      "defaultFront": "1"
    },
    "AttributeLists": {
      "FullOptions": [],
      "Keywords": [
        "HERO",
        "DEATH",
        "UNIQUE",
        "FLY",
        "NIGHTHAUNT",
        "WARD (6+)",
        "CAVALRY",
        "WIZARD (1)"
      ]
    },
    "RuleIds": {},
    "ProfileIds": [
      "profile_ea83-60f1-bd67-d25"
    ],
    "OptionListIds": []
  },
  {
    "Id": "unit_625-d4af-9738-48ca",
    "Name": "Knight of Shrouds",
    "Attributes": {
      "category": "Infantry Hero",
      "army": "Nighthaunt",
      "height": "",
      "type": "",
      "defaultFront": "1"
    },
    "AttributeLists": {
      "FullOptions": [],
      "Keywords": [
        "HERO",
        "DEATH",
        "FLY",
        "NIGHTHAUNT",
        "INFANTRY",
        "WARD (6+)"
      ]
    },
    "RuleIds": {},
    "ProfileIds": [
      "profile_625-d4af-9738-48ca"
    ],
    "OptionListIds": []
  },
  {
    "Id": "unit_9b2f-951a-816b-94c4",
    "Name": "Kurdoss Valentian, the Craven King",
    "Attributes": {
      "category": "Infantry Hero",
      "army": "Nighthaunt",
      "height": "",
      "type": "",
      "defaultFront": "1"
    },
    "AttributeLists": {
      "FullOptions": [],
      "Keywords": [
        "HERO",
        "DEATH",
        "UNIQUE",
        "FLY",
        "NIGHTHAUNT",
        "INFANTRY",
        "WARD (6+)"
      ]
    },
    "RuleIds": {},
    "ProfileIds": [
      "profile_9b2f-951a-816b-94c4"
    ],
    "OptionListIds": []
  },
  {
    "Id": "unit_d8ef-7494-db04-b1a9",
    "Name": "Awlrach the Drowner",
    "Attributes": {
      "category": "War Machine",
      "army": "Nighthaunt",
      "height": "",
      "type": "",
      "defaultFront": "1"
    },
    "AttributeLists": {
      "FullOptions": [],
      "Keywords": [
        "HERO",
        "DEATH",
        "UNIQUE",
        "FLY",
        "NIGHTHAUNT",
        "WARD (6+)",
        "WAR MACHINE"
      ]
    },
    "RuleIds": {},
    "ProfileIds": [
      "profile_d8ef-7494-db04-b1a9"
    ],
    "OptionListIds": []
  },
  {
    "Id": "unit_ee75-82ec-9c18-397b",
    "Name": "Lady Olynder, Mortarch of Grief",
    "Attributes": {
      "category": "Infantry Hero",
      "army": "Nighthaunt",
      "height": "",
      "type": "",
      "defaultFront": "1"
    },
    "AttributeLists": {
      "FullOptions": [],
      "Keywords": [
        "HERO",
        "DEATH",
        "UNIQUE",
        "FLY",
        "WARMASTER",
        "NIGHTHAUNT",
        "WIZARD (2)",
        "WARD (4+)",
        "INFANTRY"
      ]
    },
    "RuleIds": {},
    "ProfileIds": [
      "profile_ee75-82ec-9c18-397b"
    ],
    "OptionListIds": []
  },
  {
    "Id": "unit_c35d-289f-9b39-a9aa",
    "Name": "Tomb Banshee",
    "Attributes": {
      "category": "Infantry Hero",
      "army": "Nighthaunt",
      "height": "",
      "type": "",
      "defaultFront": "1"
    },
    "AttributeLists": {
      "FullOptions": [],
      "Keywords": [
        "HERO",
        "DEATH",
        "FLY",
        "NIGHTHAUNT",
        "INFANTRY",
        "WARD (6+)"
      ]
    },
    "RuleIds": {},
    "ProfileIds": [
      "profile_c35d-289f-9b39-a9aa"
    ],
    "OptionListIds": []
  },
  {
    "Id": "unit_72d-cbfa-2680-9e66",
    "Name": "Knight of Shrouds on Ethereal Steed",
    "Attributes": {
      "category": "Cavalry Hero",
      "army": "Nighthaunt",
      "height": "",
      "type": "",
      "defaultFront": "1"
    },
    "AttributeLists": {
      "FullOptions": [],
      "Keywords": [
        "HERO",
        "DEATH",
        "FLY",
        "NIGHTHAUNT",
        "WARD (6+)",
        "CAVALRY"
      ]
    },
    "RuleIds": {},
    "ProfileIds": [
      "profile_72d-cbfa-2680-9e66"
    ],
    "OptionListIds": []
  },
  {
    "Id": "unit_eac-95c-b449-a7a5",
    "Name": "Cairn Wraith",
    "Attributes": {
      "category": "Infantry Hero",
      "army": "Nighthaunt",
      "height": "",
      "type": "",
      "defaultFront": "1"
    },
    "AttributeLists": {
      "FullOptions": [],
      "Keywords": [
        "HERO",
        "DEATH",
        "FLY",
        "NIGHTHAUNT",
        "INFANTRY",
        "WARD (6+)"
      ]
    },
    "RuleIds": {},
    "ProfileIds": [
      "profile_eac-95c-b449-a7a5"
    ],
    "OptionListIds": []
  },
  {
    "Id": "unit_d5e7-8080-3243-6c22",
    "Name": "Krulghast Cruciator",
    "Attributes": {
      "category": "Infantry Hero",
      "army": "Nighthaunt",
      "height": "",
      "type": "",
      "defaultFront": "1"
    },
    "AttributeLists": {
      "FullOptions": [],
      "Keywords": [
        "HERO",
        "DEATH",
        "FLY",
        "NIGHTHAUNT",
        "INFANTRY",
        "WARD (6+)"
      ]
    },
    "RuleIds": {},
    "ProfileIds": [
      "profile_d5e7-8080-3243-6c22"
    ],
    "OptionListIds": []
  },
  {
    "Id": "unit_8bd-370e-5881-48fb",
    "Name": "Lord Executioner",
    "Attributes": {
      "category": "Infantry Hero",
      "army": "Nighthaunt",
      "height": "",
      "type": "",
      "defaultFront": "1"
    },
    "AttributeLists": {
      "FullOptions": [],
      "Keywords": [
        "HERO",
        "DEATH",
        "FLY",
        "NIGHTHAUNT",
        "INFANTRY",
        "WARD (5+)"
      ]
    },
    "RuleIds": {},
    "ProfileIds": [
      "profile_8bd-370e-5881-48fb"
    ],
    "OptionListIds": []
  },
  {
    "Id": "unit_8639-e146-50ea-6d7",
    "Name": "Dreadblade Harrows",
    "Attributes": {
      "category": "Cavalry",
      "army": "Nighthaunt",
      "height": "",
      "type": "",
      "defaultFront": "3"
    },
    "AttributeLists": {
      "FullOptions": [],
      "Keywords": [
        "DEATH",
        "FLY",
        "NIGHTHAUNT",
        "WARD (6+)",
        "CAVALRY"
      ]
    },
    "RuleIds": {},
    "ProfileIds": [
      "profile_8639-e146-50ea-6d7"
    ],
    "OptionListIds": []
  },
  {
    "Id": "unit_da26-4319-1b6a-9f32",
    "Name": "Spirit Torment",
    "Attributes": {
      "category": "Infantry Hero",
      "army": "Nighthaunt",
      "height": "",
      "type": "",
      "defaultFront": "1"
    },
    "AttributeLists": {
      "FullOptions": [],
      "Keywords": [
        "HERO",
        "DEATH",
        "FLY",
        "NIGHTHAUNT",
        "INFANTRY",
        "WARD (6+)"
      ]
    },
    "RuleIds": {},
    "ProfileIds": [
      "profile_da26-4319-1b6a-9f32"
    ],
    "OptionListIds": []
  },
  {
    "Id": "unit_76b8-eb95-f916-c5b5",
    "Name": "Guardian of Souls",
    "Attributes": {
      "category": "Infantry Hero",
      "army": "Nighthaunt",
      "height": "",
      "type": "",
      "defaultFront": "1"
    },
    "AttributeLists": {
      "FullOptions": [],
      "Keywords": [
        "HERO",
        "DEATH",
        "FLY",
        "NIGHTHAUNT",
        "INFANTRY",
        "WARD (6+)",
        "WIZARD (1)"
      ]
    },
    "RuleIds": {},
    "ProfileIds": [
      "profile_76b8-eb95-f916-c5b5"
    ],
    "OptionListIds": []
  },
  {
    "Id": "unit_bd18-dcfd-b081-f533",
    "Name": "Scriptor Mortis",
    "Attributes": {
      "category": "Infantry Hero",
      "army": "Nighthaunt",
      "height": "",
      "type": "",
      "defaultFront": "1"
    },
    "AttributeLists": {
      "FullOptions": [],
      "Keywords": [
        "HERO",
        "DEATH",
        "FLY",
        "NIGHTHAUNT",
        "INFANTRY",
        "WARD (6+)"
      ]
    },
    "RuleIds": {},
    "ProfileIds": [
      "profile_bd18-dcfd-b081-f533"
    ],
    "OptionListIds": []
  },
  {
    "Id": "unit_5f08-4648-c0e8-e7d9",
    "Name": "Pyregheists",
    "Attributes": {
      "category": "Infantry",
      "army": "Nighthaunt",
      "height": "",
      "type": "",
      "defaultFront": "5"
    },
    "AttributeLists": {
      "FullOptions": [],
      "Keywords": [
        "INFANTRY",
        "WARD (6+)",
        "DEATH",
        "CHAMPION (1/8)",
        "FLY",
        "NIGHTHAUNT"
      ]
    },
    "RuleIds": {},
    "ProfileIds": [
      "profile_5f08-4648-c0e8-e7d9"
    ],
    "OptionListIds": []
  },
  {
    "Id": "unit_4b64-f4ae-a675-d024",
    "Name": "Bladegheist Revenants",
    "Attributes": {
      "category": "Infantry",
      "army": "Nighthaunt",
      "height": "",
      "type": "",
      "defaultFront": "5"
    },
    "AttributeLists": {
      "FullOptions": [],
      "Keywords": [
        "INFANTRY",
        "WARD (6+)",
        "DEATH",
        "FLY",
        "NIGHTHAUNT"
      ]
    },
    "RuleIds": {},
    "ProfileIds": [
      "profile_4b64-f4ae-a675-d024"
    ],
    "OptionListIds": []
  },
  {
    "Id": "unit_e823-b88c-bee5-17a1",
    "Name": "Spirit Hosts",
    "Attributes": {
      "category": "Infantry",
      "army": "Nighthaunt",
      "height": "",
      "type": "",
      "defaultFront": "5"
    },
    "AttributeLists": {
      "FullOptions": [],
      "Keywords": [
        "INFANTRY",
        "WARD (6+)",
        "DEATH",
        "FLY",
        "NIGHTHAUNT"
      ]
    },
    "RuleIds": {},
    "ProfileIds": [
      "profile_e823-b88c-bee5-17a1"
    ],
    "OptionListIds": []
  },
  {
    "Id": "unit_5ca1-5e5e-cb29-238b",
    "Name": "Chainrasps",
    "Attributes": {
      "category": "Infantry",
      "army": "Nighthaunt",
      "height": "",
      "type": "",
      "defaultFront": "5"
    },
    "AttributeLists": {
      "FullOptions": [],
      "Keywords": [
        "INFANTRY",
        "WARD (6+)",
        "DEATH",
        "CHAMPION",
        "FLY",
        "NIGHTHAUNT"
      ]
    },
    "RuleIds": {},
    "ProfileIds": [
      "profile_5ca1-5e5e-cb29-238b"
    ],
    "OptionListIds": []
  },
  {
    "Id": "unit_29fe-d90b-4dde-c891",
    "Name": "Black Coach",
    "Attributes": {
      "category": "War Machine",
      "army": "Nighthaunt",
      "height": "",
      "type": "",
      "defaultFront": "1"
    },
    "AttributeLists": {
      "FullOptions": [],
      "Keywords": [
        "DEATH",
        "FLY",
        "NIGHTHAUNT",
        "WARD (6+)",
        "WAR MACHINE"
      ]
    },
    "RuleIds": {},
    "ProfileIds": [
      "profile_29fe-d90b-4dde-c891"
    ],
    "OptionListIds": []
  },
  {
    "Id": "unit_4550-ab13-9a71-205c",
    "Name": "Chainghasts",
    "Attributes": {
      "category": "Infantry",
      "army": "Nighthaunt",
      "height": "",
      "type": "",
      "defaultFront": "5"
    },
    "AttributeLists": {
      "FullOptions": [],
      "Keywords": [
        "INFANTRY",
        "WARD (6+)",
        "DEATH",
        "CHAMPION",
        "FLY",
        "NIGHTHAUNT"
      ]
    },
    "RuleIds": {},
    "ProfileIds": [
      "profile_4550-ab13-9a71-205c"
    ],
    "OptionListIds": []
  },
  {
    "Id": "unit_1cc8-87db-4e0c-223e",
    "Name": "Grimghast Reapers",
    "Attributes": {
      "category": "Infantry",
      "army": "Nighthaunt",
      "height": "",
      "type": "",
      "defaultFront": "5"
    },
    "AttributeLists": {
      "FullOptions": [],
      "Keywords": [
        "INFANTRY",
        "WARD (6+)",
        "DEATH",
        "CHAMPION",
        "FLY",
        "NIGHTHAUNT"
      ]
    },
    "RuleIds": {},
    "ProfileIds": [
      "profile_1cc8-87db-4e0c-223e"
    ],
    "OptionListIds": []
  },
  {
    "Id": "unit_88e9-d216-bef6-b4fe",
    "Name": "Craventhrone Guard",
    "Attributes": {
      "category": "Infantry",
      "army": "Nighthaunt",
      "height": "",
      "type": "",
      "defaultFront": "5"
    },
    "AttributeLists": {
      "FullOptions": [],
      "Keywords": [
        "INFANTRY",
        "WARD (6+)",
        "DEATH",
        "CHAMPION",
        "FLY",
        "NIGHTHAUNT",
        "STANDARD BEARER (1/5)"
      ]
    },
    "RuleIds": {},
    "ProfileIds": [
      "profile_88e9-d216-bef6-b4fe"
    ],
    "OptionListIds": []
  },
  {
    "Id": "unit_43ee-d90-fdd8-e998",
    "Name": "Glaivewraith Stalkers",
    "Attributes": {
      "category": "Infantry",
      "army": "Nighthaunt",
      "height": "",
      "type": "",
      "defaultFront": "5"
    },
    "AttributeLists": {
      "FullOptions": [],
      "Keywords": [
        "INFANTRY",
        "WARD (6+)",
        "DEATH",
        "FLY",
        "NIGHTHAUNT",
        "MUSICIAN (1/4)"
      ]
    },
    "RuleIds": {},
    "ProfileIds": [
      "profile_43ee-d90-fdd8-e998"
    ],
    "OptionListIds": []
  },
  {
    "Id": "unit_ca83-a38b-b1c6-f4e6",
    "Name": "Myrmourn Banshees",
    "Attributes": {
      "category": "Infantry",
      "army": "Nighthaunt",
      "height": "",
      "type": "",
      "defaultFront": "5"
    },
    "AttributeLists": {
      "FullOptions": [],
      "Keywords": [
        "INFANTRY",
        "WARD (6+)",
        "DEATH",
        "FLY",
        "NIGHTHAUNT"
      ]
    },
    "RuleIds": {},
    "ProfileIds": [
      "profile_ca83-a38b-b1c6-f4e6"
    ],
    "OptionListIds": []
  },
  {
    "Id": "unit_1a20-8b80-4ae3-5168",
    "Name": "Dreadscythe Harridans",
    "Attributes": {
      "category": "Infantry",
      "army": "Nighthaunt",
      "height": "",
      "type": "",
      "defaultFront": "5"
    },
    "AttributeLists": {
      "FullOptions": [],
      "Keywords": [
        "INFANTRY",
        "WARD (6+)",
        "DEATH",
        "FLY",
        "NIGHTHAUNT",
        "CHAMPION"
      ]
    },
    "RuleIds": {},
    "ProfileIds": [
      "profile_1a20-8b80-4ae3-5168"
    ],
    "OptionListIds": []
  },
  {
    "Id": "unit_66a0-f02f-2616-3c62",
    "Name": "Hexwraiths",
    "Attributes": {
      "category": "Cavalry",
      "army": "Nighthaunt",
      "height": "",
      "type": "",
      "defaultFront": "3"
    },
    "AttributeLists": {
      "FullOptions": [],
      "Keywords": [
        "WARD (6+)",
        "DEATH",
        "CHAMPION",
        "FLY",
        "NIGHTHAUNT",
        "CAVALRY"
      ]
    },
    "RuleIds": {},
    "ProfileIds": [
      "profile_66a0-f02f-2616-3c62"
    ],
    "OptionListIds": []
  },
  {
    "Id": "unit_4225-5446-8a69-146b",
    "Name": "Vault of Souls",
    "Attributes": {
      "category": "Endless Spell",
      "army": "Nighthaunt",
      "height": "",
      "type": "",
      "defaultFront": "1"
    },
    "AttributeLists": {
      "FullOptions": [],
      "Keywords": [
        "DEATH",
        "WARD (6+)",
        "MANIFESTATION",
        "ENDLESS SPELL",
        "FLY",
        "NIGHTHAUNT"
      ]
    },
    "RuleIds": {},
    "ProfileIds": [
      "profile_4225-5446-8a69-146b"
    ],
    "OptionListIds": []
  },
  {
    "Id": "unit_8fe3-71b-c0fd-506b",
    "Name": "Shyish Reaper",
    "Attributes": {
      "category": "Endless Spell",
      "army": "Nighthaunt",
      "height": "",
      "type": "",
      "defaultFront": "1"
    },
    "AttributeLists": {
      "FullOptions": [],
      "Keywords": [
        "DEATH",
        "WARD (6+)",
        "MANIFESTATION",
        "ENDLESS SPELL",
        "FLY",
        "NIGHTHAUNT"
      ]
    },
    "RuleIds": {},
    "ProfileIds": [
      "profile_8fe3-71b-c0fd-506b"
    ],
    "OptionListIds": []
  },
  {
    "Id": "unit_68d8-b0b8-90b9-d60d",
    "Name": "Mortalis Terminexus",
    "Attributes": {
      "category": "Endless Spell",
      "army": "Nighthaunt",
      "height": "",
      "type": "",
      "defaultFront": "1"
    },
    "AttributeLists": {
      "FullOptions": [],
      "Keywords": [
        "DEATH",
        "WARD (6+)",
        "MANIFESTATION",
        "ENDLESS SPELL",
        "FLY",
        "NIGHTHAUNT"
      ]
    },
    "RuleIds": {},
    "ProfileIds": [
      "profile_68d8-b0b8-90b9-d60d"
    ],
    "OptionListIds": []
  },
  {
    "Id": "unit_378f-c709-a843-3f3e",
    "Name": "Thorns of the Briar Queen",
    "Attributes": {
      "category": "Infantry",
      "army": "Nighthaunt",
      "height": "",
      "type": "",
      "defaultFront": "5"
    },
    "AttributeLists": {
      "FullOptions": [],
      "Keywords": [
        "INFANTRY",
        "UNIQUE",
        "Legends",
        "WARD (6+)",
        "DEATH",
        "NIGHTHAUNT",
        "FLY"
      ]
    },
    "RuleIds": {},
    "ProfileIds": [
      "profile_378f-c709-a843-3f3e"
    ],
    "OptionListIds": []
  },
  {
    "Id": "unit_a074-2ecb-5d24-8c4e",
    "Name": "The Headsmen's Curse",
    "Attributes": {
      "category": "Infantry",
      "army": "Nighthaunt",
      "height": "",
      "type": "",
      "defaultFront": "5"
    },
    "AttributeLists": {
      "FullOptions": [],
      "Keywords": [
        "INFANTRY",
        "UNIQUE",
        "Legends",
        "CHAMPION",
        "WARD (6+)",
        "DEATH",
        "NIGHTHAUNT",
        "FLY"
      ]
    },
    "RuleIds": {},
    "ProfileIds": [
      "profile_a074-2ecb-5d24-8c4e"
    ],
    "OptionListIds": []
  },
  {
    "Id": "unit_e4c1-f020-bd21-780a",
    "Name": "Black Coach (Scourge of Ghyran)",
    "Attributes": {
      "category": "War Machine",
      "army": "Nighthaunt",
      "height": "",
      "type": "",
      "defaultFront": "1"
    },
    "AttributeLists": {
      "FullOptions": [],
      "Keywords": [
        "DEATH",
        "FLY",
        "NIGHTHAUNT",
        "WARD (6+)",
        "WAR MACHINE"
      ]
    },
    "RuleIds": {},
    "ProfileIds": [
      "profile_e4c1-f020-bd21-780a"
    ],
    "OptionListIds": []
  },
  {
    "Id": "unit_4bd5-32fb-6e98-2357",
    "Name": "Kurdoss Valentian, the Craven King (Scourge of Ghyran)",
    "Attributes": {
      "category": "Infantry Hero",
      "army": "Nighthaunt",
      "height": "",
      "type": "",
      "defaultFront": "1"
    },
    "AttributeLists": {
      "FullOptions": [],
      "Keywords": [
        "HERO",
        "DEATH",
        "UNIQUE",
        "FLY",
        "NIGHTHAUNT",
        "INFANTRY",
        "WARD (6+)"
      ]
    },
    "RuleIds": {},
    "ProfileIds": [
      "profile_4bd5-32fb-6e98-2357"
    ],
    "OptionListIds": []
  },
  {
    "Id": "unit_ca5e-5353-81bc-4e13",
    "Name": "Nexus of Grief",
    "Attributes": {
      "category": "Faction Terrain",
      "army": "Nighthaunt",
      "height": "",
      "type": "",
      "defaultFront": "1"
    },
    "AttributeLists": {
      "FullOptions": [],
      "Keywords": [
        "DEATH",
        "FACTION TERRAIN",
        "NIGHTHAUNT",
        "WARD (5+)"
      ]
    },
    "RuleIds": {},
    "ProfileIds": [
      "profile_ca5e-5353-81bc-4e13"
    ],
    "OptionListIds": []
  }
]