[
  {
    "Id": "profile_95eb-6e32-fd0f-7b39",
    "Name": "Bladebringer, Herald on Exalted Chariot",
    "RuleIds": {
      "rule_b6c5-d7db-cdde-9884": "Soulgorgers",
      "rule_2227-a3c3-63a4-efdf": "Mutilating Blades"
    },
    "Statlines": [
      {
        "Name": "Bladebringer, Herald on Exalted Chariot",
        "Values": {
          "Move": "10\"",
          "Health": "12",
          "Save": "4+",
          "Control": "2"
        },
        "RuleIds": {}
      }
    ],
    "EquipmentIds": [
      "equipment_ff7c-2782-44a7-6013",
      "equipment_562f-609f-ce0c-17ed"
    ],
    "Base": {
      "Shape": "round",
      "Size": {
        "width": "92",
        "length": "120"
      }
    }
  },
  {
    "Id": "profile_288-b306-7776-96b5",
    "Name": "Shalaxi Helbane",
    "RuleIds": {
      "rule_7e9d-6c7-e6aa-88b2": "Excess of Violence",
      "rule_67ca-3436-910-c622": "Paramount Hunter",
      "rule_bbd0-62b7-cb3a-68a9": "Supernatural Grace",
      "rule_5ce3-79b1-1338-f8ec": "Refine Senses",
      "rule_bbd4-a864-c34-9fe6": "Battle Damaged"
    },
    "Statlines": [
      {
        "Name": "Shalaxi Helbane",
        "Values": {
          "Move": "14\"",
          "Health": "16",
          "Save": "4+",
          "Control": "5"
        },
        "RuleIds": {}
      }
    ],
    "EquipmentIds": [
      "equipment_443a-7539-773b-c04b",
      "equipment_b859-1a8e-b99b-96d8"
    ],
    "Base": {
      "Shape": "round",
      "Size": {
        "width": "100",
        "length": "100"
      }
    }
  },
  {
    "Id": "profile_19fa-187-b059-ffce",
    "Name": "The Masque",
    "RuleIds": {
      "rule_4be4-1dbc-986c-28f2": "The Endless Dance",
      "rule_9f28-f70-c560-158f": "Staff of Masks"
    },
    "Statlines": [
      {
        "Name": "The Masque",
        "Values": {
          "Move": "8\"",
          "Health": "5",
          "Save": "5+",
          "Control": "2"
        },
        "RuleIds": {}
      }
    ],
    "EquipmentIds": [
      "equipment_1d15-ad9d-ffb-6088"
    ],
    "Base": {
      "Shape": "round",
      "Size": {
        "width": "32",
        "length": "32"
      }
    }
  },
  {
    "Id": "profile_a172-db1d-3ad4-c354",
    "Name": "Sigvald, Prince of Slaanesh",
    "RuleIds": {
      "rule_c741-a37c-d1dd-2922": "Shardslash",
      "rule_9cd3-71bf-b0bc-c9a1": "The Glorious Reborn",
      "rule_4940-f42a-8dca-ba24": "Powered by Vainglory"
    },
    "Statlines": [
      {
        "Name": "Sigvald, Prince of Slaanesh",
        "Values": {
          "Move": "6\"",
          "Health": "7",
          "Save": "3+",
          "Control": "2"
        },
        "RuleIds": {}
      }
    ],
    "EquipmentIds": [
      "equipment_6924-5205-6a01-f4b2"
    ],
    "Base": {
      "Shape": "round",
      "Size": {
        "width": "40",
        "length": "40"
      }
    }
  },
  {
    "Id": "profile_7c43-7c1e-d92c-f199",
    "Name": "Dexcessa, Talon of Slaanesh",
    "RuleIds": {
      "rule_33fa-e63b-972e-b465": "Joyous Battle Fury",
      "rule_376b-72a-a3ac-faa8": "Redolence of Violence",
      "rule_e38f-3ebf-80ca-50cc": "Fleeting Dance of Death",
      "rule_f1eb-18bc-1827-e173": "Scion of Slaanesh"
    },
    "Statlines": [
      {
        "Name": "Dexcessa, Talon of Slaanesh",
        "Values": {
          "Move": "12\"",
          "Health": "10",
          "Save": "5+",
          "Control": "5"
        },
        "RuleIds": {}
      }
    ],
    "EquipmentIds": [
      "equipment_b78e-152c-3d2d-74f9"
    ],
    "Base": {
      "Shape": "round",
      "Size": {
        "width": "100",
        "length": "100"
      }
    }
  },
  {
    "Id": "profile_4011-5d78-a180-3c22",
    "Name": "Keeper of Secrets",
    "RuleIds": {
      "rule_3202-5f34-c593-6008": "Locus of Slaanesh",
      "rule_fac7-e6a2-3799-be9d": "Dark Temptations",
      "rule_ef74-ce62-b83d-127f": "Supernatural Grace",
      "rule_1bff-adc2-c078-9207": "Cacophonic Choir",
      "rule_32e1-9355-edf-c70": "Battle Damaged"
    },
    "Statlines": [
      {
        "Name": "Keeper of Secrets",
        "Values": {
          "Move": "12\"",
          "Health": "16",
          "Save": "4+",
          "Control": "5"
        },
        "RuleIds": {}
      }
    ],
    "EquipmentIds": [
      "equipment_6fd-4e16-ac1a-934c",
      "equipment_ea65-458f-a4c2-2040"
    ],
    "Base": {
      "Shape": "round",
      "Size": {
        "width": "100",
        "length": "100"
      }
    }
  },
  {
    "Id": "profile_7ff4-32c2-f67e-5476",
    "Name": "Contorted Epitome",
    "RuleIds": {
      "rule_c149-4284-d4f8-abc9": "Horrible Fascination",
      "rule_2819-fbe5-f4b6-d237": "Swallow Energy"
    },
    "Statlines": [
      {
        "Name": "Contorted Epitome",
        "Values": {
          "Move": "9\"",
          "Health": "7",
          "Save": "5+",
          "Control": "2"
        },
        "RuleIds": {}
      }
    ],
    "EquipmentIds": [
      "equipment_8da1-842f-fe5c-7d55"
    ],
    "Base": {
      "Shape": "round",
      "Size": {
        "width": "70",
        "length": "105"
      }
    }
  },
  {
    "Id": "profile_89b7-8cfa-f458-12c0",
    "Name": "Syll'Esske, the Vengeful Allegiance",
    "RuleIds": {
      "rule_227d-2ea1-06b0-ffb6": "The Vengeful Allegiance",
      "rule_bfd2-0423-ba2e-d2c5": "Subvert",
      "rule_6a9b-eb36-8676-a47a": "Deadly Symbiosis"
    },
    "Statlines": [
      {
        "Name": "Syll'Esske, the Vengeful Allegiance",
        "Values": {
          "Move": "8\"",
          "Health": "9",
          "Save": "4+",
          "Control": "4"
        },
        "RuleIds": {}
      }
    ],
    "EquipmentIds": [
      "equipment_63fc-cf16-21fe-2041",
      "equipment_fc7a-cca3-892f-f432"
    ],
    "Base": {
      "Shape": "round",
      "Size": {
        "width": "80",
        "length": "80"
      }
    }
  },
  {
    "Id": "profile_27ef-714f-2f7-3770",
    "Name": "Shardspeaker of Slaanesh",
    "RuleIds": {
      "rule_3e1c-89b2-8934-e4f0": "Mist Lurkers",
      "rule_5f99-7d41-9196-8cad": "Twisted Mirror"
    },
    "Statlines": [
      {
        "Name": "Shardspeaker of Slaanesh",
        "Values": {
          "Move": "6\"",
          "Health": "5",
          "Save": "5+",
          "Control": "2"
        },
        "RuleIds": {}
      }
    ],
    "EquipmentIds": [
      "equipment_b24c-a58f-3c3b-4dfa",
      "equipment_145d-efc5-ecdc-e7d7"
    ],
    "Base": {
      "Shape": "round",
      "Size": {
        "width": "32",
        "length": "32"
      }
    }
  },
  {
    "Id": "profile_4b99-af35-44db-7fd8",
    "Name": "Seeker Chariot",
    "RuleIds": {
      "rule_bc71-d656-79e0-2aa0": "Mutilating Blades"
    },
    "Statlines": [
      {
        "Name": "Seeker Chariot",
        "Values": {
          "Move": "12\"",
          "Health": "6",
          "Save": "4+",
          "Control": "2"
        },
        "RuleIds": {}
      }
    ],
    "EquipmentIds": [
      "equipment_1b07-4857-fb31-8df3",
      "equipment_e74-75c5-9d61-3930"
    ],
    "Base": {
      "Shape": "round",
      "Size": {
        "width": "92",
        "length": "120"
      }
    }
  },
  {
    "Id": "profile_f41c-5481-64ee-8868",
    "Name": "Hellflayer",
    "RuleIds": {
      "rule_d087-e01-a337-cc67": "Soulscent",
      "rule_3689-4fe6-8401-be4c": "Threshing Doom"
    },
    "Statlines": [
      {
        "Name": "Hellflayer",
        "Values": {
          "Move": "10\"",
          "Health": "7",
          "Save": "4+",
          "Control": "2"
        },
        "RuleIds": {}
      }
    ],
    "EquipmentIds": [
      "equipment_24ee-ccb5-749b-94a3",
      "equipment_4d8b-5b7a-91eb-1bb0",
      "equipment_6f7b-b915-7bc7-720"
    ],
    "Base": {
      "Shape": "round",
      "Size": {
        "width": "92",
        "length": "120"
      }
    }
  },
  {
    "Id": "profile_de32-60a4-2468-ea8a",
    "Name": "Slaangor Fiendbloods",
    "RuleIds": {
      "rule_8d5f-41b0-5b25-65ee": "Slaughter at Any Cost"
    },
    "Statlines": [
      {
        "Name": "Slaangor Fiendbloods",
        "Values": {
          "Move": "6\"",
          "Health": "3",
          "Save": "5+",
          "Control": "1"
        },
        "RuleIds": {}
      }
    ],
    "EquipmentIds": [
      "equipment_b24-4e9a-fb7f-78cd"
    ],
    "Base": {
      "Shape": "round",
      "Size": {
        "width": "40",
        "length": "40"
      }
    }
  },
  {
    "Id": "profile_ebde-c823-a0d7-dce1",
    "Name": "Seekers",
    "RuleIds": {
      "rule_9061-824b-247-e9b2": "Quicksilver Speed"
    },
    "Statlines": [
      {
        "Name": "Seekers",
        "Values": {
          "Move": "12\"",
          "Health": "3",
          "Save": "5+",
          "Control": "1"
        },
        "RuleIds": {}
      }
    ],
    "EquipmentIds": [
      "equipment_a9f2-cbcb-bda5-f55f",
      "equipment_fa62-a2c1-68dc-19dd"
    ],
    "Base": {
      "Shape": "round",
      "Size": {
        "width": "35",
        "length": "60"
      }
    }
  },
  {
    "Id": "profile_7516-fef5-83f7-22a7",
    "Name": "Blissbarb Archers",
    "RuleIds": {
      "rule_4e44-7769-baad-8488": "Blissbrew Homonculus"
    },
    "Statlines": [
      {
        "Name": "Blissbarb Archers",
        "Values": {
          "Move": "6\"",
          "Health": "1",
          "Save": "6+",
          "Control": "1"
        },
        "RuleIds": {}
      }
    ],
    "EquipmentIds": [
      "equipment_e51b-dd14-8e1-2858",
      "equipment_283b-8492-5f37-f8e1"
    ],
    "Base": {
      "Shape": "round",
      "Size": {
        "width": "28",
        "length": "28"
      }
    }
  },
  {
    "Id": "profile_eb63-b209-7932-2b43",
    "Name": "Synessa, the Voice of Slaanesh",
    "RuleIds": {
      "rule_a7e7-1b3b-186a-a62b": "Voice of Slaanesh",
      "rule_f9b8-cb9-1d14-9e4f": "Paramount Hunter",
      "rule_8c4e-bb82-97f7-e41b": "Supernatural Grace",
      "rule_7a9a-5e84-438c-46f0": "Whispers of Doubt",
      "rule_751b-5650-d224-50fb": "Progeny of Slaanesh"
    },
    "Statlines": [
      {
        "Name": "Synessa, the Voice of Slaanesh",
        "Values": {
          "Move": "12\"",
          "Health": "10",
          "Save": "5+",
          "Control": "5"
        },
        "RuleIds": {}
      }
    ],
    "EquipmentIds": [
      "equipment_ab87-8d39-e41b-98c6",
      "equipment_a297-1781-b89d-594a"
    ],
    "Base": {
      "Shape": "round",
      "Size": {
        "width": "100",
        "length": "100"
      }
    }
  },
  {
    "Id": "profile_37ec-d134-cffd-d637",
    "Name": "Infernal Enrapturess, Herald of Slaanesh",
    "RuleIds": {
      "rule_fc5-1a98-e08b-e3ac": "Discordant Disruption"
    },
    "Statlines": [
      {
        "Name": "Infernal Enrapturess, Herald of Slaanesh",
        "Values": {
          "Move": "6\"",
          "Health": "5",
          "Save": "5+",
          "Control": "2"
        },
        "RuleIds": {}
      }
    ],
    "EquipmentIds": [
      "equipment_2b16-91f7-6b7-e088",
      "equipment_9f9e-7b03-a980-25b1"
    ],
    "Base": {
      "Shape": "round",
      "Size": {
        "width": "32",
        "length": "32"
      }
    }
  },
  {
    "Id": "profile_ef1b-a791-66b4-735f",
    "Name": "Lord of Hubris",
    "RuleIds": {
      "rule_803d-7041-688b-7465": "'You First, I Insist...'",
      "rule_c6ee-6eac-45e7-40": "Only the Best Will Suffice"
    },
    "Statlines": [
      {
        "Name": "Lord of Hubris",
        "Values": {
          "Move": "6\"",
          "Health": "5",
          "Save": "5+",
          "Control": "2"
        },
        "RuleIds": {}
      }
    ],
    "EquipmentIds": [
      "equipment_1725-5e7b-8731-d9c9"
    ],
    "Base": {
      "Shape": "round",
      "Size": {
        "width": "40",
        "length": "40"
      }
    }
  },
  {
    "Id": "profile_fac2-b0a0-feec-f70f",
    "Name": "Glutos Orscollion, Lord of Gluttony",
    "RuleIds": {
      "rule_437b-af31-be16-73ff": "Gorge on Excess",
      "rule_67e3-1d88-9bb4-4906": "The Grand Gourmand",
      "rule_28b9-9c9b-3e06-d093": "Crippling Famishment",
      "rule_8dce-246a-9a52-2f1f": "Battle Damaged"
    },
    "Statlines": [
      {
        "Name": "Glutos Orscollion, Lord of Gluttony",
        "Values": {
          "Move": "8\"",
          "Health": "18",
          "Save": "4+",
          "Control": "5"
        },
        "RuleIds": {}
      }
    ],
    "EquipmentIds": [
      "equipment_2aff-b1ef-a37-346e",
      "equipment_1fe1-6e73-10df-192b",
      "equipment_bca8-26ff-fc30-f6f0"
    ],
    "Base": {
      "Shape": "round",
      "Size": {
        "width": "100",
        "length": "130"
      }
    }
  },
  {
    "Id": "profile_1a3b-a566-401c-d9c4",
    "Name": "Blissbarb Seekers",
    "RuleIds": {
      "rule_182-3414-a33-bfd5": "Glory Shots"
    },
    "Statlines": [
      {
        "Name": "Blissbarb Seekers",
        "Values": {
          "Move": "12\"",
          "Health": "4",
          "Save": "5+",
          "Control": "1"
        },
        "RuleIds": {}
      }
    ],
    "EquipmentIds": [
      "equipment_416e-9820-785b-c50c",
      "equipment_280-d0db-f110-a3ae",
      "equipment_ef3f-4b94-55d6-ffe0"
    ],
    "Base": {
      "Shape": "round",
      "Size": {
        "width": "35",
        "length": "60"
      }
    }
  },
  {
    "Id": "profile_4890-8c79-a2bd-b1ad",
    "Name": "Lord of Pain",
    "RuleIds": {
      "rule_4dbb-5331-8d9-71f0": "Share the Pain",
      "rule_11ae-d853-35ff-940": "Disciples in Torment"
    },
    "Statlines": [
      {
        "Name": "Lord of Pain",
        "Values": {
          "Move": "6\"",
          "Health": "5",
          "Save": "4+",
          "Control": "2"
        },
        "RuleIds": {}
      }
    ],
    "EquipmentIds": [
      "equipment_60b2-99d4-3c64-bb3c"
    ],
    "Base": {
      "Shape": "round",
      "Size": {
        "width": "40",
        "length": "40"
      }
    }
  },
  {
    "Id": "profile_973c-d5a3-65d4-2eaa",
    "Name": "Fiends",
    "RuleIds": {
      "rule_5768-e54b-a5b1-551b": "Soporific Musk",
      "rule_3514-4717-2801-de82": "Disruptive Song"
    },
    "Statlines": [
      {
        "Name": "Fiends",
        "Values": {
          "Move": "10\"",
          "Health": "4",
          "Save": "5+",
          "Control": "1"
        },
        "RuleIds": {}
      }
    ],
    "EquipmentIds": [
      "equipment_5610-4a5f-9667-9ae2"
    ],
    "Base": {
      "Shape": "round",
      "Size": {
        "width": "42",
        "length": "75"
      }
    }
  },
  {
    "Id": "profile_73f4-30e5-20b1-cf47",
    "Name": "Daemonettes",
    "RuleIds": {
      "rule_ac85-9d4-4f3-20cb": "Lithe and Swift"
    },
    "Statlines": [
      {
        "Name": "Daemonettes",
        "Values": {
          "Move": "6\"",
          "Health": "1",
          "Save": "6+",
          "Control": "1"
        },
        "RuleIds": {}
      }
    ],
    "EquipmentIds": [
      "equipment_c893-1604-484b-54db"
    ],
    "Base": {
      "Shape": "round",
      "Size": {
        "width": "25",
        "length": "25"
      }
    }
  },
  {
    "Id": "profile_af06-7271-8760-4a4",
    "Name": "Myrmidesh Painbringers",
    "RuleIds": {
      "rule_b838-7d26-f8e-4459": "Paragons of Battle"
    },
    "Statlines": [
      {
        "Name": "Myrmidesh Painbringers",
        "Values": {
          "Move": "6\"",
          "Health": "2",
          "Save": "3+",
          "Control": "1"
        },
        "RuleIds": {}
      }
    ],
    "EquipmentIds": [
      "equipment_c6f9-db86-3060-a5aa"
    ],
    "Base": {
      "Shape": "round",
      "Size": {
        "width": "32",
        "length": "32"
      }
    }
  },
  {
    "Id": "profile_ffcf-47e1-a14f-b507",
    "Name": "Symbaresh Twinsouls",
    "RuleIds": {
      "rule_b175-ab7b-fea9-d0b3": "Fiendish Reflexes",
      "rule_59d5-6aa3-aa0f-1366": "Ego-driven Excess"
    },
    "Statlines": [
      {
        "Name": "Symbaresh Twinsouls",
        "Values": {
          "Move": "6\"",
          "Health": "2",
          "Save": "4+",
          "Control": "1"
        },
        "RuleIds": {}
      }
    ],
    "EquipmentIds": [
      "equipment_7a93-23c9-a457-c60f"
    ],
    "Base": {
      "Shape": "round",
      "Size": {
        "width": "32",
        "length": "32"
      }
    }
  },
  {
    "Id": "profile_7fbf-a41a-7e29-8476",
    "Name": "Hellstriders",
    "RuleIds": {
      "rule_cae7-f1a6-3289-a02b": "Fiendish Reflexes"
    },
    "Statlines": [
      {
        "Name": "Hellstriders",
        "Values": {
          "Move": "12\"",
          "Health": "3",
          "Save": "5+",
          "Control": "1"
        },
        "RuleIds": {}
      }
    ],
    "EquipmentIds": [
      "equipment_cbfc-b62d-8343-4ca9",
      "equipment_1368-c238-dc70-5ff8"
    ],
    "Base": {
      "Shape": "round",
      "Size": {
        "width": "35",
        "length": "60"
      }
    }
  },
  {
    "Id": "profile_395d-b625-25a4-4ca2",
    "Name": "Slickblade Seekers",
    "RuleIds": {
      "rule_8ac5-5bbf-1b9f-924a": "Unrivalled Velocity"
    },
    "Statlines": [
      {
        "Name": "Slickblade Seekers",
        "Values": {
          "Move": "12\"",
          "Health": "4",
          "Save": "5+",
          "Control": "1"
        },
        "RuleIds": {}
      }
    ],
    "EquipmentIds": [
      "equipment_9ab6-29dc-f8bd-f053",
      "equipment_ecb8-a522-77e6-96b4"
    ],
    "Base": {
      "Shape": "round",
      "Size": {
        "width": "35",
        "length": "60"
      }
    }
  },
  {
    "Id": "profile_61ca-47bf-34ed-c847",
    "Name": "Mesmerising Mirror",
    "RuleIds": {
      "rule_f9cc-c081-f892-7a32": "Gaze Not Into Its Depths",
      "rule_e5a4-7244-ba41-bf08": "Irresistible Lure"
    },
    "Statlines": [
      {
        "Name": "Mesmerising Mirror",
        "Values": {},
        "RuleIds": {}
      }
    ],
    "EquipmentIds": [],
    "Base": {
      "Shape": "round",
      "Size": {
        "width": "50",
        "length": "50"
      }
    }
  },
  {
    "Id": "profile_25c4-8769-f67a-78c3",
    "Name": "Dreadful Visage",
    "RuleIds": {
      "rule_f517-1df1-a892-9bb4": "Flensing Tongues"
    },
    "Statlines": [
      {
        "Name": "Dreadful Visage",
        "Values": {},
        "RuleIds": {}
      }
    ],
    "EquipmentIds": [
      "equipment_6928-3fcf-1d93-b846"
    ],
    "Base": {
      "Shape": "round",
      "Size": {
        "width": "50",
        "length": "50"
      }
    }
  },
  {
    "Id": "profile_14ec-16c5-a9d2-7252",
    "Name": "Wheels of Excruciation",
    "RuleIds": {
      "rule_d542-f481-422-a7d6": "Exquisite Agony"
    },
    "Statlines": [
      {
        "Name": "Wheels of Excruciation",
        "Values": {},
        "RuleIds": {}
      }
    ],
    "EquipmentIds": [
      "equipment_17bc-20ba-bd86-d15e"
    ],
    "Base": {
      "Shape": "round",
      "Size": {
        "width": "50",
        "length": "50"
      }
    }
  },
  {
    "Id": "profile_bad2-41cf-b054-d9b3",
    "Name": "Fane of Slaanesh",
    "RuleIds": {
      "rule_c0aa-df5e-6df8-f65d": "Damned Conduit"
    },
    "Statlines": [
      {
        "Name": "Fane of Slaanesh",
        "Values": {
          "Move": "-",
          "Health": "10",
          "Save": "4+",
          "Control": "-"
        },
        "RuleIds": {}
      }
    ],
    "EquipmentIds": [],
    "Base": {
      "Shape": "round",
      "Size": {
        "width": "80",
        "length": "130"
      }
    }
  },
  {
    "Id": "profile_08e6-7dfb-f60e-6fc0",
    "Name": "Exalted Chariot",
    "RuleIds": {
      "rule_e5cf-5a69-cd18-5649": "Excess of Blades"
    },
    "Statlines": [
      {
        "Name": "Exalted Chariot",
        "Values": {
          "Move": "10\"",
          "Health": "9",
          "Save": "4+",
          "Control": "2"
        },
        "RuleIds": {}
      }
    ],
    "EquipmentIds": [
      "equipment_76e9-71da-06c5-3ac2",
      "equipment_e8d7-b59b-871c-3ae5"
    ],
    "Base": {
      "Shape": "round",
      "Size": {
        "width": "92",
        "length": "120"
      }
    }
  },
  {
    "Id": "profile_1ad6-bbe6-59c2-0716",
    "Name": "Bladebringer, Herald on Seeker Chariot",
    "RuleIds": {
      "rule_fb00-3973-b1ea-7e07": "Thrillseeking Cavalcade",
      "rule_21d0-34da-4788-3712": "Mutilating Blades"
    },
    "Statlines": [
      {
        "Name": "Bladebringer, Herald on Seeker Chariot",
        "Values": {
          "Move": "12\"",
          "Health": "8",
          "Save": "4+",
          "Control": "2"
        },
        "RuleIds": {}
      }
    ],
    "EquipmentIds": [
      "equipment_e4f5-7f18-022a-9bc6",
      "equipment_59cf-e553-17f5-11db"
    ],
    "Base": {
      "Shape": "round",
      "Size": {
        "width": "92",
        "length": "120"
      }
    }
  },
  {
    "Id": "profile_5c8d-d6ce-1035-6969",
    "Name": "Bladebringer, Herald on Hellflayer",
    "RuleIds": {
      "rule_fd0c-e7ec-0cf0-8a45": "Slavering for Sensation",
      "rule_f7cf-80e8-902d-e297": "Soulscent",
      "rule_eeee-9aa0-8466-5b42": "Threshing Doom"
    },
    "Statlines": [
      {
        "Name": "Bladebringer, Herald on Hellflayer",
        "Values": {
          "Move": "10\"",
          "Health": "8",
          "Save": "4+",
          "Control": "2"
        },
        "RuleIds": {}
      }
    ],
    "EquipmentIds": [
      "equipment_0e04-3f4b-c799-696b",
      "equipment_1f0d-951d-a341-d4a5",
      "equipment_9f2d-9331-ec8f-2a88"
    ],
    "Base": {
      "Shape": "round",
      "Size": {
        "width": "92",
        "length": "120"
      }
    }
  },
  {
    "Id": "profile_5886-d643-7104-b3be",
    "Name": "Viceleader, Herald of Slaanesh",
    "RuleIds": {
      "rule_dfb0-d32c-405b-a440": "Lust for Violence",
      "rule_975d-8991-69ec-c947": "Lithe and Swift"
    },
    "Statlines": [
      {
        "Name": "Viceleader, Herald of Slaanesh",
        "Values": {
          "Move": "6\"",
          "Health": "5",
          "Save": "5+",
          "Control": "2"
        },
        "RuleIds": {}
      }
    ],
    "EquipmentIds": [
      "equipment_abaa-5c0c-df9a-df13"
    ],
    "Base": {
      "Shape": "round",
      "Size": {
        "width": "32",
        "length": "32"
      }
    }
  },
  {
    "Id": "profile_a2e9-3905-f6de-5053",
    "Name": "The Thricefold Discord",
    "RuleIds": {
      "rule_c6bc-678a-009d-f24f": "Indulgence Given Form",
      "rule_ded0-5f05-9f9c-9940": "Sublime Harmonies"
    },
    "Statlines": [
      {
        "Name": "The Thricefold Discord",
        "Values": {
          "Move": "6\"",
          "Health": "3",
          "Save": "5+",
          "Control": "1"
        },
        "RuleIds": {}
      }
    ],
    "EquipmentIds": [
      "equipment_14d2-d926-8e25-813b",
      "equipment_84e7-2d94-a362-a268",
      "equipment_aced-16fb-3dec-dbfb"
    ],
    "Base": {
      "Shape": "round",
      "Size": {
        "width": "92",
        "length": "120"
      }
    }
  },
  {
    "Id": "profile_3ae1-3009-26f6-69a1",
    "Name": "The Dread Pageant",
    "RuleIds": {
      "rule_6fbe-55ef-18b2-5475": "Slicing Fervour",
      "rule_9d14-5d8d-2f31-327a": "Blissbarb Shafts"
    },
    "Statlines": [
      {
        "Name": "The Dread Pageant",
        "Values": {
          "Move": "6\"",
          "Health": "3",
          "Save": "5+",
          "Control": "1"
        },
        "RuleIds": {}
      }
    ],
    "EquipmentIds": [
      "equipment_0ff8-7729-6273-5db8",
      "equipment_47d1-a594-1955-e8a7",
      "equipment_3084-2ebc-35ba-e31d",
      "equipment_dd55-dbca-5b8d-abdc"
    ],
    "Base": {
      "Shape": "round",
      "Size": {
        "width": "32",
        "length": "32"
      }
    }
  },
  {
    "Id": "profile_8d85-ce05-2e48-02e9",
    "Name": "Syll'Esske, the Vengeful Allegiance (Scourge of Ghyran)",
    "RuleIds": {
      "rule_64e9-6359-bfa9-48f8": "Wandering Minds",
      "rule_f9f0-b860-9f86-708f": "Violent Offerings",
      "rule_54d7-ea45-2331-be59": "Champions of the Gilded Throne"
    },
    "Statlines": [
      {
        "Name": "Syll'Esske, the Vengeful Allegiance (Scourge of Ghyran)",
        "Values": {
          "Move": "8\"",
          "Health": "9",
          "Save": "4+",
          "Control": "4"
        },
        "RuleIds": {}
      }
    ],
    "EquipmentIds": [
      "equipment_657e-bcee-7e22-48f4",
      "equipment_8c42-9076-8291-60a1"
    ],
    "Base": {
      "Shape": "round",
      "Size": {
        "width": "80",
        "length": "80"
      }
    }
  },
  {
    "Id": "profile_3e9a-0e86-a7fa-ec3d",
    "Name": "Slaangor Fiendbloods (Scourge of Ghyran)",
    "RuleIds": {
      "rule_011e-21ef-4971-1ee1": "Veiled Threat",
      "rule_aa8e-3cbb-0c5b-6eef": "Bestial Onslaught",
      "rule_e585-f2f2-5809-5a1b": "Instinctive Advance"
    },
    "Statlines": [
      {
        "Name": "Slaangor Fiendbloods (Scourge of Ghyran)",
        "Values": {
          "Move": "6\"",
          "Health": "3",
          "Save": "5+",
          "Control": "1"
        },
        "RuleIds": {}
      }
    ],
    "EquipmentIds": [
      "equipment_da26-48fe-711d-e904"
    ],
    "Base": {
      "Shape": "round",
      "Size": {
        "width": "40",
        "length": "40"
      }
    }
  }
]