[
  {
    "Id": "68526efc9ec085f701067990",
    "Name": "Pirate Lord",
    "Attributes": {
      "category": "Lords",
      "army": "Pirates of Sartosa",
      "height": "Standard",
      "type": "",
      "defaultFront": "1"
    },
    "AttributeLists": {
      "FullOptions": []
    },
    "RuleIds": {},
    "OptionListIds": [],
    "ProfileIds": [
      "68526efc9ec085f701067990"
    ]
  },
  {
    "Id": "68526efc9ec085f701067c6d",
    "Name": "Sorcerer Lord",
    "Attributes": {
      "category": "Lords",
      "army": "Pirates of Sartosa",
      "height": "Standard",
      "type": "",
      "defaultFront": "1"
    },
    "AttributeLists": {
      "FullOptions": []
    },
    "RuleIds": {},
    "OptionListIds": [],
    "ProfileIds": [
      "68526efc9ec085f701067c6d"
    ]
  },
  {
    "Id": "68526efc9ec085f7010680f1",
    "Name": "Special Characters",
    "Attributes": {
      "category": "Lords",
      "army": "Pirates of Sartosa",
      "height": "Standard",
      "type": "",
      "defaultFront": "1"
    },
    "AttributeLists": {
      "FullOptions": [
        "Aranessa Saltspite, the Queen of Tides",
        "Carmen Sicilieri, the Pirate Princess",
        "Jaego Roth, Captain of the Heldenhammer",
        "Giacchino de Falco, the Crazed Captain"
      ]
    },
    "RuleIds": {},
    "OptionListIds": [],
    "ProfileIds": [
      "68526efc9ec085f7010680f7"
    ]
  },
  {
    "Id": "68526f019ec085f70106895f",
    "Name": "First Mate",
    "Attributes": {
      "category": "Heroes",
      "army": "Pirates of Sartosa",
      "height": "Standard",
      "type": "",
      "defaultFront": "1"
    },
    "AttributeLists": {
      "FullOptions": []
    },
    "RuleIds": {},
    "OptionListIds": [],
    "ProfileIds": [
      "68526f019ec085f70106895f"
    ]
  },
  {
    "Id": "68526f029ec085f701068c9f",
    "Name": "Pirate Captain",
    "Attributes": {
      "category": "Heroes",
      "army": "Pirates of Sartosa",
      "height": "Standard",
      "type": "",
      "defaultFront": "1"
    },
    "AttributeLists": {
      "FullOptions": []
    },
    "RuleIds": {},
    "OptionListIds": [],
    "ProfileIds": [
      "68526f029ec085f701068c9f"
    ]
  },
  {
    "Id": "68526f029ec085f701068f7c",
    "Name": "Pirate Sorcerer",
    "Attributes": {
      "category": "Heroes",
      "army": "Pirates of Sartosa",
      "height": "Standard",
      "type": "",
      "defaultFront": "1"
    },
    "AttributeLists": {
      "FullOptions": []
    },
    "RuleIds": {},
    "OptionListIds": [],
    "ProfileIds": [
      "68526f029ec085f701068f7c"
    ]
  },
  {
    "Id": "68526f029ec085f7010693b8",
    "Name": "Regiments of Renown",
    "Attributes": {
      "category": "Heroes",
      "army": "Pirates of Sartosa",
      "height": "Standard",
      "type": "",
      "defaultFront": "1"
    },
    "AttributeLists": {
      "FullOptions": [
        "Asarnil the Dragonlord",
        "The Witch Hunters"
      ]
    },
    "RuleIds": {},
    "OptionListIds": [
      "a4a3bc32-850a-41f1-bcee-9484a5c13388",
      "5ce9dcd0-8531-4154-9498-f1741396e181"
    ],
    "ProfileIds": [
      "68526f029ec085f7010693be"
    ]
  },
  {
    "Id": "68526f069ec085f7010698c0",
    "Name": "Special Characters",
    "Attributes": {
      "category": "Heroes",
      "army": "Pirates of Sartosa",
      "height": "Standard",
      "type": "",
      "defaultFront": "1"
    },
    "AttributeLists": {
      "FullOptions": [
        "Mr. Bill",
        "Krusher the Anchorman",
        "Doctor \"Doc\" Exmelin",
        "Fleur and Estella"
      ]
    },
    "RuleIds": {},
    "OptionListIds": [
      "a1fd986b-68d3-4d95-b185-aece1f9a0d5b",
      "59721132-1d0c-4892-8b66-7307b6d0d13d",
      "014b51b3-c545-4b36-8a8e-9a567cda004a",
      "391aecd3-f610-42bf-a798-4be25ddbe264"
    ],
    "ProfileIds": [
      "68526f069ec085f7010698c6"
    ]
  },
  {
    "Id": "68526f0f9ec085f70106a1b8",
    "Name": "Buccaneers",
    "Attributes": {
      "category": "Core",
      "army": "Pirates of Sartosa",
      "height": "Standard",
      "type": "",
      "defaultFront": "5"
    },
    "AttributeLists": {
      "FullOptions": []
    },
    "RuleIds": {},
    "OptionListIds": [],
    "ProfileIds": [
      "68526f0f9ec085f70106a1bb"
    ]
  },
  {
    "Id": "68526f109ec085f70106a347",
    "Name": "Deck Gunners",
    "Attributes": {
      "category": "Core",
      "army": "Pirates of Sartosa",
      "height": "Standard",
      "type": "",
      "defaultFront": "5"
    },
    "AttributeLists": {
      "FullOptions": [
        "Standard Bearer"
      ]
    },
    "RuleIds": {},
    "OptionListIds": [],
    "ProfileIds": [
      "68526f109ec085f70106a34a"
    ]
  },
  {
    "Id": "68526f119ec085f70106a782",
    "Name": "Harpooners",
    "Attributes": {
      "category": "Core",
      "army": "Pirates of Sartosa",
      "height": "Standard",
      "type": "",
      "defaultFront": "5"
    },
    "AttributeLists": {
      "FullOptions": []
    },
    "RuleIds": {},
    "OptionListIds": [],
    "ProfileIds": [
      "68526f119ec085f70106a785"
    ]
  },
  {
    "Id": "68526f129ec085f70106a90e",
    "Name": "Pirate Crew",
    "Attributes": {
      "category": "Core",
      "army": "Pirates of Sartosa",
      "height": "Standard",
      "type": "",
      "defaultFront": "5"
    },
    "AttributeLists": {
      "FullOptions": [
        "Standard Bearer"
      ]
    },
    "RuleIds": {},
    "OptionListIds": [],
    "ProfileIds": [
      "68526f129ec085f70106a911"
    ]
  },
  {
    "Id": "68526f149ec085f70106ad5d",
    "Name": "Swabbies",
    "Attributes": {
      "category": "Core",
      "army": "Pirates of Sartosa",
      "height": "Standard",
      "type": "",
      "defaultFront": "5"
    },
    "AttributeLists": {
      "FullOptions": [
        "Champion"
      ]
    },
    "RuleIds": {},
    "OptionListIds": [],
    "ProfileIds": [
      "68526f149ec085f70106ad61"
    ]
  },
  {
    "Id": "68526f159ec085f70106b085",
    "Name": "Deck Cannon",
    "Attributes": {
      "category": "Special",
      "army": "Pirates of Sartosa",
      "height": "Standard",
      "type": "",
      "defaultFront": "1"
    },
    "AttributeLists": {
      "FullOptions": []
    },
    "RuleIds": {},
    "OptionListIds": [],
    "ProfileIds": [
      "68526f159ec085f70106b085"
    ]
  },
  {
    "Id": "68526f159ec085f70106b21b",
    "Name": "Dwarf Sea Dogs",
    "Attributes": {
      "category": "Special",
      "army": "Pirates of Sartosa",
      "height": "Standard",
      "type": "",
      "defaultFront": "5"
    },
    "AttributeLists": {
      "FullOptions": [
        "Standard Bearer"
      ]
    },
    "RuleIds": {},
    "OptionListIds": [],
    "ProfileIds": [
      "68526f159ec085f70106b21e"
    ]
  },
  {
    "Id": "68526f179ec085f70106b602",
    "Name": "Grog Lubbers",
    "Attributes": {
      "category": "Special",
      "army": "Pirates of Sartosa",
      "height": "Standard",
      "type": "",
      "defaultFront": "5"
    },
    "AttributeLists": {
      "FullOptions": [
        "Standard Bearer"
      ]
    },
    "RuleIds": {},
    "OptionListIds": [],
    "ProfileIds": [
      "68526f179ec085f70106b605"
    ]
  },
  {
    "Id": "68526f199ec085f70106b917",
    "Name": "Norse Reavers",
    "Attributes": {
      "category": "Special",
      "army": "Pirates of Sartosa",
      "height": "Standard",
      "type": "",
      "defaultFront": "5"
    },
    "AttributeLists": {
      "FullOptions": [
        "Standard Bearer",
        "Musician",
        "Champion"
      ]
    },
    "RuleIds": {},
    "OptionListIds": [
      "0551c8f5-3977-4a0b-952a-27d98d1abcca"
    ],
    "ProfileIds": [
      "68526f199ec085f70106b91a"
    ]
  },
  {
    "Id": "68526f1e9ec085f70106c0ee",
    "Name": "Orc Freebooterz",
    "Attributes": {
      "category": "Special",
      "army": "Pirates of Sartosa",
      "height": "Standard",
      "type": "",
      "defaultFront": "5"
    },
    "AttributeLists": {
      "FullOptions": [
        "Standard Bearer",
        "Musician",
        "Champion"
      ]
    },
    "RuleIds": {},
    "OptionListIds": [
      "6f56c78e-ee83-42ff-8fbe-d7951e3f5366"
    ],
    "ProfileIds": [
      "68526f1e9ec085f70106c0f1"
    ]
  },
  {
    "Id": "68526f229ec085f70106c8b1",
    "Name": "Powder Monkeys",
    "Attributes": {
      "category": "Special",
      "army": "Pirates of Sartosa",
      "height": "Standard",
      "type": "",
      "defaultFront": "5"
    },
    "AttributeLists": {
      "FullOptions": [
        "Standard Bearer"
      ]
    },
    "RuleIds": {},
    "OptionListIds": [],
    "ProfileIds": [
      "68526f229ec085f70106c8b4"
    ]
  },
  {
    "Id": "68526f249ec085f70106ccd8",
    "Name": "Regiments of Renown",
    "Attributes": {
      "category": "Special",
      "army": "Pirates of Sartosa",
      "height": "Standard",
      "type": "",
      "defaultFront": "5"
    },
    "AttributeLists": {
      "FullOptions": [
        "Pirazzo's Lost Legion",
        "Leopold's Leopard Company",
        "The Alcatani Fellowship",
        "Ricco's Republican Guard",
        "Marksmen of Miragliano",
        "Braganza's Besiegers",
        "Captain Edvard Van Der Kraal & Manann's Blades",
        "Al Muktar's Desert Dogs",
        "Voland's Venators",
        "Vespero's Vendetta",
        "Long Drong's Slayer Pirates",
        "Standard Bearer",
        "Musician"
      ]
    },
    "RuleIds": {},
    "OptionListIds": [
      "88ca1867-18c1-4046-bb9b-6059022746b2",
      "ab283cc0-069a-4279-8a40-ae6c47f7bab5",
      "e02d00ca-234c-4f12-bde1-c1b4939be66b",
      "fb4ac4e4-63cb-417d-82ab-760815d2f0d8",
      "1737fd73-bd29-443c-a12f-c0ab4669bc9c",
      "7b668880-5340-4e96-804d-d2eae3c3b8aa",
      "0b654ae7-acf3-4d66-8f33-063a1131c9f9",
      "2bc17b7a-32c9-478a-b9a6-ae3e61678053",
      "ebe04c2c-d748-4f3b-a98b-4bbc0824b771",
      "b72512be-525e-4358-8755-7f7a43ee0f07",
      "48f13cbd-09f7-408f-98b5-a0c31b3e7a2e"
    ],
    "ProfileIds": [
      "68526f249ec085f70106cd10",
      "68526f249ec085f70106cf2c",
      "68526f249ec085f70106cf2d"
    ]
  },
  {
    "Id": "68526f479ec085f70106ee51",
    "Name": "Ship's Mates",
    "Attributes": {
      "category": "Special",
      "army": "Pirates of Sartosa",
      "height": "Standard",
      "type": "",
      "defaultFront": "5"
    },
    "AttributeLists": {
      "FullOptions": [
        "Standard Bearer"
      ]
    },
    "RuleIds": {},
    "OptionListIds": [],
    "ProfileIds": [
      "68526f479ec085f70106ee5b"
    ]
  },
  {
    "Id": "68526f499ec085f70106f2ae",
    "Name": "Sons of Stromfels",
    "Attributes": {
      "category": "Special",
      "army": "Pirates of Sartosa",
      "height": "Standard",
      "type": "",
      "defaultFront": "3"
    },
    "AttributeLists": {
      "FullOptions": [
        "Champion"
      ]
    },
    "RuleIds": {},
    "OptionListIds": [
      "f7eaee59-8f6f-4198-ad3e-c9da6aa6918b"
    ],
    "ProfileIds": [
      "68526f499ec085f70106f2b1"
    ]
  },
  {
    "Id": "68526f4a9ec085f70106f5bb",
    "Name": "Swivel Gunners",
    "Attributes": {
      "category": "Special",
      "army": "Pirates of Sartosa",
      "height": "Standard",
      "type": "",
      "defaultFront": "5"
    },
    "AttributeLists": {
      "FullOptions": []
    },
    "RuleIds": {},
    "OptionListIds": [],
    "ProfileIds": [
      "68526f4a9ec085f70106f5be"
    ]
  },
  {
    "Id": "68526f4a9ec085f70106f73d",
    "Name": "Wokou Raiders",
    "Attributes": {
      "category": "Special",
      "army": "Pirates of Sartosa",
      "height": "Standard",
      "type": "",
      "defaultFront": "5"
    },
    "AttributeLists": {
      "FullOptions": [
        "Standard Bearer",
        "Musician",
        "Champion"
      ]
    },
    "RuleIds": {},
    "OptionListIds": [
      "5a9ea134-6969-4a9e-a454-de2f04fd00a3"
    ],
    "ProfileIds": [
      "68526f4a9ec085f70106f740"
    ]
  },
  {
    "Id": "68526f4e9ec085f70106ff00",
    "Name": "Dark Maidens",
    "Attributes": {
      "category": "Rare",
      "army": "Pirates of Sartosa",
      "height": "Standard",
      "type": "",
      "defaultFront": "3"
    },
    "AttributeLists": {
      "FullOptions": [
        "Champion"
      ]
    },
    "RuleIds": {},
    "OptionListIds": [
      "479eb2e9-cb01-4622-a8cf-1cc6b2728fc5"
    ],
    "ProfileIds": [
      "68526f4e9ec085f70106ff03"
    ]
  },
  {
    "Id": "68526f4f9ec085f701070203",
    "Name": "Flying Galley",
    "Attributes": {
      "category": "Rare",
      "army": "Pirates of Sartosa",
      "height": "Standard",
      "type": "",
      "defaultFront": "1"
    },
    "AttributeLists": {
      "FullOptions": []
    },
    "RuleIds": {},
    "OptionListIds": [],
    "ProfileIds": [
      "68526f4f9ec085f701070203"
    ]
  },
  {
    "Id": "68526f4f9ec085f701070385",
    "Name": "Hell-Hammer Cannon",
    "Attributes": {
      "category": "Rare",
      "army": "Pirates of Sartosa",
      "height": "Standard",
      "type": "",
      "defaultFront": "1"
    },
    "AttributeLists": {
      "FullOptions": [
        "Hell-Hammer Cannon",
        "Tripple Barrel Cannon",
        "Ironfist Mortar"
      ]
    },
    "RuleIds": {},
    "OptionListIds": [
      "c32efd7c-60fc-429c-80db-72abd81b8af4",
      "46b29740-9cc2-4ceb-a1e7-030819d16277",
      "ebe57f78-893b-43cc-aa55-42ded5113104"
    ],
    "ProfileIds": [
      "68526f4f9ec085f70107038b"
    ]
  },
  {
    "Id": "68526f569ec085f701070a4d",
    "Name": "Regiments of Renown",
    "Attributes": {
      "category": "Rare",
      "army": "Pirates of Sartosa",
      "height": "Standard",
      "type": "",
      "defaultFront": "5"
    },
    "AttributeLists": {
      "FullOptions": [
        "The Birdmen of Catrazza",
        "Anakonda's Amazons",
        "Lumpin Croop's Fighting Cocks",
        "Beorg Bearstruck and the Bearmen of Urslo",
        "Golgfag's Mercenary Ogres",
        "Ogla Khan's Wolfboyz",
        "Ruglud's Armoured Orcs",
        "Tichi-Huichi's Raiders",
        "Mengil Manhide's Manflayers",
        "The Cursed Company",
        "Bronzino's Galloper Guns",
        "The Giants of Albion",
        "Standard Bearer",
        "Musician"
      ]
    },
    "RuleIds": {},
    "OptionListIds": [
      "05d921db-054b-406c-9f17-fa92331c9691",
      "718d062a-7ef4-4837-9e32-9a3bc575a000",
      "df92c863-c26f-4270-a2c4-bab68ce6beb5",
      "1a973f38-cffc-442e-a33a-15d51090445a",
      "79a24b07-d257-46a8-8ad2-5c054ff59699",
      "1db3e69f-4cc6-4954-8976-eca8a830ea9a",
      "14b581bb-5bb6-4d06-b9ae-06b3a377debc",
      "95664118-1496-47b9-a810-337865158a85",
      "2882c70d-0bd5-4923-b048-4ca8c5b9e9bc",
      "f75c7591-fffd-463f-b9c0-42ef64a20221",
      "63ecb931-afae-464c-ab25-5fdcc705c719",
      "e8f11dcb-bcfe-4477-accb-524d111951dc"
    ],
    "ProfileIds": [
      "68526f569ec085f701070a8d"
    ]
  },
  {
    "Id": "68526f7c9ec085f701072ece",
    "Name": "Sea Giant",
    "Attributes": {
      "category": "Rare",
      "army": "Pirates of Sartosa",
      "height": "Standard",
      "type": "",
      "defaultFront": "1"
    },
    "AttributeLists": {
      "FullOptions": []
    },
    "RuleIds": {},
    "OptionListIds": [],
    "ProfileIds": [
      "68526f7c9ec085f701072ece"
    ]
  },
  {
    "Id": "68526f7c9ec085f701073041",
    "Name": "Sea Serpent Riders",
    "Attributes": {
      "category": "Rare",
      "army": "Pirates of Sartosa",
      "height": "Standard",
      "type": "",
      "defaultFront": "3"
    },
    "AttributeLists": {
      "FullOptions": [
        "Standard Bearer"
      ]
    },
    "RuleIds": {},
    "OptionListIds": [],
    "ProfileIds": [
      "68526f7c9ec085f701073044"
    ]
  },
  {
    "Id": "68526f7e9ec085f701073422",
    "Name": "Turtigon Battle Platform",
    "Attributes": {
      "category": "Rare",
      "army": "Pirates of Sartosa",
      "height": "Standard",
      "type": "",
      "defaultFront": "1"
    },
    "AttributeLists": {
      "FullOptions": []
    },
    "RuleIds": {},
    "OptionListIds": [],
    "ProfileIds": [
      "68526f7e9ec085f701073422"
    ]
  }
]